hello_tea/__init__.py
hello_tea/main.py
hello_tea-0.2.dist-info/LICENSE
hello_tea-0.2.dist-info/METADATA
hello_tea-0.2.dist-info/WHEEL
hello_tea-0.2.dist-info/entry_points.txt
hello_tea-0.2.dist-info/top_level.txt
hello_tea-0.2.dist-info/RECORD
