Metadata-Version: 2.1
Name: hello-tea
Version: 0.2
Summary: hello tea oss projects
Home-page: https://github.com/akronoo/hello_tea
Author: akronoo
Author-email: 
Project-URL: Bug Tracker, https://github.com/akronoo/hello_tea
Project-URL: Documentation, https://github.com/akronoo/hello_tea
Project-URL: Source Code, https://github.com/akronoo/hello_tea
Classifier: Programming Language :: Python :: 3
Classifier: License :: OSI Approved :: MIT License
Classifier: Operating System :: OS Independent
License-File: LICENSE
Requires-Dist: Pillow
Requires-Dist: numpy
